keto/__about__.py
keto/__init__.py
keto-0.0.0.dist-info/LICENSE
keto-0.0.0.dist-info/METADATA
keto-0.0.0.dist-info/WHEEL
keto-0.0.0.dist-info/top_level.txt
keto-0.0.0.dist-info/RECORD
